{
    "key": 14,
    "texts": [
        "<p>梅摇了摇头，你瞥见她绿色的双眼里闪过一丝积攒已久的愤怒。</p>",
        "<p>“他总是开太快，就好像那条路是他自己家的一样。几年前他撞死过一匹母马，那可是相当地可怕。你也看见那辆车成了什么模样。车上的那些毛病都够吓着你了。”</p>",
        "<p>她抿了一口茶，视线掠过你，注视着房间的角落。</p>",
        "<p>“然而，我们既然住在这里，就实在不能得罪这个人。他是我们联系外面大世界的唯一方式，而且他心眼并不坏。我觉得人在同一条路上走十五年，会变得粗心大意。你该原谅他才是。”</p>",
        "<p>梅又沉默了好一会儿。然后，她的目光再次转回你。</p>",
        "<p>“但你来这儿不是听我唠叨的，你肯定也饿了。我可以给你凑一点炖菜。你觉得如何？”</p>",
        "<p>你又问了一遍她要价多少，梅讲了个相当便宜的价钱，你毫不犹豫地接受了。这间房子虽小但舒适，炖菜熟烂又丰盛。吃过饭以后，离你平常睡觉的时间还有几个小时。</p>"
    ],
    "options": [
        { "key": 0, "text": "和梅多聊聊天" },
        { "key": 1, "text": "到外面转转，确认自己的方位" },
        { "key": 2, "text": "提前上床早睡觉" }
    ]
}