{
    "key": 6,
    "texts": [
        "<p>你漫步在烬头村的街道上，可是并没有特别想去的地方。这村子建在一片相对平坦的高地上，视野开阔，景色壮丽。",
        "向北看去，白山山脉朦胧的峰顶高耸入云；向南眺望，温尼伯索基湖粼粼的湖水天水相接。</p>",
        "<p>这个村子只需要不到五分钟就能从一头走到另一头。你来到西面的盘山路。还有一条路通向南边，再转向东，从另一侧的山脊下坡延伸出去。",
        "村子西南角有一片开阔的草地，包围着一座坍圮的教堂，它的墓地正位于悬崖的最高点。还有三条大道，朝东北方向交汇到一座刻有浮雕的黑色金属建筑物。它十分突兀，直指蓝天。</p>",
        "<img src='images/map.png'>",
        "<p>现在你可以：</p>"
    ],
    "options": [
        { "key": 0, "text": "去本地杂货店询问交通方式" },
        { "key": 1, "text": "找到村会堂" },
        { "key": 2, "text": "沿着道路下坡，查看东盘山路" },
        { "key": 3, "text": "调查巨大的金属建筑物" },
        { "key": 4, "text": "探索教堂" },
        { "key": 5, "text": "寻找拥有交通工具的当地居民" }
    ]
}